data_preprocessing_library_sevvalcucuk_asudesozcu/CategoricalEncoder.py
data_preprocessing_library_sevvalcucuk_asudesozcu/DataTypeConverter.py
data_preprocessing_library_sevvalcucuk_asudesozcu/DateTimeHandler.py
data_preprocessing_library_sevvalcucuk_asudesozcu/FeatureEngineer.py
data_preprocessing_library_sevvalcucuk_asudesozcu/MissingValueHandler.py
data_preprocessing_library_sevvalcucuk_asudesozcu/OutlierHandling.py
data_preprocessing_library_sevvalcucuk_asudesozcu/Scaler.py
data_preprocessing_library_sevvalcucuk_asudesozcu/TextCleaner.py
data_preprocessing_library_sevvalcucuk_asudesozcu/__init__.py
data_preprocessing_library_sevvalcucuk_asudesozcu-4.5.1.dist-info/METADATA
data_preprocessing_library_sevvalcucuk_asudesozcu-4.5.1.dist-info/WHEEL
data_preprocessing_library_sevvalcucuk_asudesozcu-4.5.1.dist-info/top_level.txt
data_preprocessing_library_sevvalcucuk_asudesozcu-4.5.1.dist-info/RECORD
